pesuacademy/__init__.py
pesuacademy/pesuacademy.py
pesuacademy/constants/__init__.py
pesuacademy/constants/fields.py
pesuacademy/exceptions/__init__.py
pesuacademy/exceptions/authentication.py
pesuacademy/exceptions/csrf.py
pesuacademy/models/__init__.py
pesuacademy/models/course.py
pesuacademy/models/profile.py
pesuacademy/pages/__init__.py
pesuacademy/pages/attendance.py
pesuacademy/pages/courses.py
pesuacademy/pages/profile.py
pesuacademy/pages/utils.py
pesuacademy-0.0.1.dist-info/LICENSE
pesuacademy-0.0.1.dist-info/METADATA
pesuacademy-0.0.1.dist-info/WHEEL
pesuacademy-0.0.1.dist-info/top_level.txt
pesuacademy-0.0.1.dist-info/RECORD
