Metadata-Version: 2.1
Name: pesuacademy
Version: 0.0.1
Summary: Python wrapper and APIs for the PESU Academy website
Home-page: https://github.com/HackerSpace-PESU/pesuacademy-py
Author: Aditeya Baral
Author-email: aditeya.baral@gmail.com
Keywords: pesu,pesu academy,api,wrapper,python
Classifier: Development Status :: 5 - Production/Stable
Classifier: Intended Audience :: Developers
Classifier: Programming Language :: Python :: 3.9
Classifier: Programming Language :: Python :: 3.10
Classifier: Programming Language :: Python :: 3.11
Classifier: License :: OSI Approved :: MIT License
Classifier: Operating System :: OS Independent
Requires-Python: >=3.9
License-File: LICENSE
Requires-Dist: requests
Requires-Dist: requests-html
Requires-Dist: beautifulsoup4
Requires-Dist: lxml-html-clean
